dumbmoney/__init__.py
dumbmoney/backtests/__init__.py
dumbmoney/backtests/single_asset.py
dumbmoney/core/__init__.py
dumbmoney/core/data.py
dumbmoney/core/portfolio.py
dumbmoney/core/results.py
dumbmoney/core/signals.py
dumbmoney/core/stock.py
dumbmoney/feeds/__init__.py
dumbmoney/feeds/akshare.py
dumbmoney/feeds/feed.py
dumbmoney/feeds/feed_service.py
dumbmoney/feeds/massive.py
dumbmoney/feeds/tiger.py
dumbmoney/feeds/tushare.py
dumbmoney/indicators/__init__.py
dumbmoney/indicators/indicator.py
dumbmoney/indicators/macd.py
dumbmoney/indicators/moving_average.py
dumbmoney/indicators/rsi.py
dumbmoney/logger.py
dumbmoney/plotting/__init__.py
dumbmoney/plotting/adapters/__init__.py
dumbmoney/plotting/adapters/macd_adapter.py
dumbmoney/plotting/mplfinance.py
dumbmoney/plotting/plotly.py
dumbmoney/plotting/plotter.py
dumbmoney/policies/__init__.py
dumbmoney/policies/naive.py
dumbmoney/policies/policy.py
dumbmoney/py.typed
dumbmoney/strategies/__init__.py
dumbmoney/strategies/ma_cross.py
dumbmoney/strategies/strategy.py
dumbmoney-0.3.2.dist-info/WHEEL
dumbmoney-0.3.2.dist-info/METADATA
dumbmoney-0.3.2.dist-info/RECORD
