Metadata-Version: 2.4
Name: dumbmoney
Version: 0.3.2
Summary: Technical analysis and quantitative trading toolkit for retail investors taking on the market
Author: littledumb
Author-email: littledumb <littledumb@dumbsmart.org>
License-Expression: MIT
Requires-Dist: akshare>=1.17.91
Requires-Dist: massive>=2.0.2
Requires-Dist: mplfinance>=0.12.10b0
Requires-Dist: pandas>=2.3.3
Requires-Dist: plotly>=6.5.0
Requires-Dist: pydantic>=2.12.5
Requires-Dist: tushare>=1.4.24
Requires-Dist: tigeropen>=3.5.2 ; extra == 'tiger'
Requires-Python: >=3.9
Project-URL: Homepage, https://github.com/dumbsmart-org/dumbmoney
Project-URL: Issues, https://github.com/dumbsmart-org/dumbmoney/issues
Project-URL: Repository, https://github.com/dumbsmart-org/dumbmoney.git
Provides-Extra: tiger
